<?xml version="1.0" encoding="utf-8"?>
<LanguageData>

	<!-- EN: Center parted -->
	<Mousekin_Hair_PartedCenter.label>중앙 분할</Mousekin_Hair_PartedCenter.label>

	<!-- EN: Side parted -->
	<Mousekin_Hair_PartedSide.label>사이드파트</Mousekin_Hair_PartedSide.label>

	<!-- EN: Mop -->
	<Mousekin_Hair_ShortMop.label>대걸레</Mousekin_Hair_ShortMop.label>

	<!-- EN: Chin bob -->
	<Mousekin_Hair_BobChin.label>친보브</Mousekin_Hair_BobChin.label>

	<!-- EN: Braided bun -->
	<Mousekin_Hair_BunBraided.label>땋은 롤빵</Mousekin_Hair_BunBraided.label>

	<!-- EN: Long -->
	<Mousekin_Hair_Long.label>긴</Mousekin_Hair_Long.label>

	<!-- EN: Long waves -->
	<Mousekin_Hair_LongWaves.label>긴 파도</Mousekin_Hair_LongWaves.label>

	<!-- EN: Pigtails -->
	<Mousekin_Hair_PlaitDouble.label>땋은 머리</Mousekin_Hair_PlaitDouble.label>

	<!-- EN: Side plait -->
	<Mousekin_Hair_PlaitSide.label>옆 엮기</Mousekin_Hair_PlaitSide.label>

	<!-- EN: Curly twintails -->
	<Mousekin_Hair_TwintailsCurly.label>곱슬머리 트윈테일</Mousekin_Hair_TwintailsCurly.label>
	
</LanguageData>